easy_events/__init__.py
easy_events/async_events.py
easy_events/events.py
easy_events/objects.py
easy_events/simple_events.py
easy_events-3.1.1.dist-info/LICENSE
easy_events-3.1.1.dist-info/METADATA
easy_events-3.1.1.dist-info/WHEEL
easy_events-3.1.1.dist-info/top_level.txt
easy_events-3.1.1.dist-info/RECORD
