Metadata-Version: 2.1
Name: easy-events
Version: 3.1.1
Summary: An universal wrapper (and useful tool) to make event / commands in python
Home-page: https://github.com/ThePhoenix78/easy-events
Download-URL: https://github.com/ThePhoenix78/easy-events/tarball/master
Author: ThePhoenix78
Author-email: thephoenix788@gmail.com
License: MIT
Keywords: wrapper,event,commands,command
Classifier: Programming Language :: Python :: 3
Classifier: License :: OSI Approved :: MIT License
Classifier: Operating System :: OS Independent
License-File: LICENSE
